covid19/__init__.py
covid19/__main__.py
covid19/fetcher.py
covid19/functions.py
covid19/helpers.py
covid19/logger.py
covid19/parser.py
covid19/printer.py
covid19_cli-1.1.2.dist-info/DESCRIPTION.rst
covid19_cli-1.1.2.dist-info/METADATA
covid19_cli-1.1.2.dist-info/RECORD
covid19_cli-1.1.2.dist-info/WHEEL
covid19_cli-1.1.2.dist-info/entry_points.txt
covid19_cli-1.1.2.dist-info/metadata.json
covid19_cli-1.1.2.dist-info/top_level.txt
